urbantz/__init__.py
urbantz/base.py
urbantz/delivery.py
urbantz/exceptions.py
urbantz/items.py
urbantz/tracker.py
urbantz/utils.py
pyurbantz-0.2.0.dist-info/LICENSE
pyurbantz-0.2.0.dist-info/METADATA
pyurbantz-0.2.0.dist-info/WHEEL
pyurbantz-0.2.0.dist-info/top_level.txt
pyurbantz-0.2.0.dist-info/RECORD
