Metadata-Version: 2.1
Name: pyurbantz
Version: 0.2.0
Summary: A helper for UrbanTZ's public undocumented API
Home-page: https://gitlab.com/Lucidiot/pyurbantz
Author: Lucidiot
License: GNU General Public License 3
Project-URL: Source Code, https://gitlab.com/Lucidiot/pyurbantz
Project-URL: GitHub Mirror, https://github.com/Lucidiot/pyurbantz
Keywords: api urbantz order delivery tracking
Platform: UNKNOWN
Classifier: Development Status :: 3 - Alpha
Classifier: License :: OSI Approved :: GNU General Public License v3 (GPLv3)
Classifier: Natural Language :: English
Classifier: Intended Audience :: Developers
Classifier: Programming Language :: Python :: 3
Classifier: Programming Language :: Python :: 3 :: Only
Classifier: Programming Language :: Python :: 3.4
Classifier: Programming Language :: Python :: 3.5
Classifier: Programming Language :: Python :: 3.6
Classifier: Programming Language :: Python :: 3.7
Classifier: Topic :: Software Development :: Libraries
Classifier: Topic :: Utilities
Requires-Dist: requests (>=2.20)
Provides-Extra: dev
Requires-Dist: flake8 (>=3.5) ; extra == 'dev'
Requires-Dist: Sphinx (>=1.8.1) ; extra == 'dev'
Requires-Dist: coverage (>=4.5) ; extra == 'dev'
Requires-Dist: codecov (>=2.0) ; extra == 'dev'
